{
"alexellis":{"rank": 1, "icon": "https://avatars.githubusercontent.com/u/6358735?u=d6331a8506a0253fd1066ade2a97338b983d0021&v=4&s=40", "name": "Alex Ellis", "commits": 16174},
"bahmutov":{"rank": 2, "icon": "https://avatars.githubusercontent.com/u/2212006?u=23b522c7384c4322687171ba919f2ed17b6fb0b4&v=4&s=40", "name": "Gleb Bahmutov", "commits": 11867},
"antfu":{"rank": 3, "icon": "https://avatars.githubusercontent.com/u/11247099?u=a83ed73998ba6f3048f3b671e6c1cd4789cc216f&v=4&s=40", "name": "Anthony Fu", "commits": 10166},
"jaywcjlove":{"rank": 4, "icon": "https://avatars.githubusercontent.com/u/1680273?u=4471b74deb9973096418a93960c664c5ea3bd159&v=4&s=40", "name": "小弟调调™", "commits": 8643},
"iliakan":{"rank": 5, "icon": "https://avatars.githubusercontent.com/u/349336?u=d64e2cf0473bd7a3a270656c6bb2b5559c7f6bb6&v=4&s=40", "name": "Ilya Kantor", "commits": 8044},
"peppy":{"rank": 6, "icon": "https://avatars.githubusercontent.com/u/191335?v=4&s=40", "name": "Dean Herbert", "commits": 7417},
"ruanyf":{"rank": 7, "icon": "https://avatars.githubusercontent.com/u/905434?v=4&s=40", "name": "Ruan YiFeng", "commits": 6591},
"ornicar":{"rank": 8, "icon": "https://avatars.githubusercontent.com/u/140370?v=4&s=40", "name": "Thibault Duplessis", "commits": 6553},
"justjavac":{"rank": 9, "icon": "https://avatars.githubusercontent.com/u/359395?u=bb50dde6882b70d87c0b074e1d4986762cf294ad&v=4&s=40", "name": "迷渡", "commits": 6263},
"MikeMcQuaid":{"rank": 10, "icon": "https://avatars.githubusercontent.com/u/125011?u=cf59848ad58616aadc6a7de81562b2364a2e19fa&v=4&s=40", "name": "Mike McQuaid", "commits": 5546},
"kroitor":{"rank": 11, "icon": "https://avatars.githubusercontent.com/u/1294454?v=4&s=40", "name": "Igor Kroitor", "commits": 5271},
"wx-chevalier":{"rank": 12, "icon": "https://avatars.githubusercontent.com/u/5803001?u=ed7b811c712791593f4cee1125d9ab2c1e4f2099&v=4&s=40", "name": "王下邀月熊", "commits": 5025},
"phodal":{"rank": 13, "icon": "https://avatars.githubusercontent.com/u/472311?u=3d7d46bf34e32449b1439178ae7652cf06d130f1&v=4&s=40", "name": "Fengda Huang", "commits": 4918},
"mathiasbynens":{"rank": 14, "icon": "https://avatars.githubusercontent.com/u/81942?u=284f01ab572101237f97e5e34d855fb580f614f5&v=4&s=40", "name": "Mathias Bynens", "commits": 4252},
"ljharb":{"rank": 15, "icon": "https://avatars.githubusercontent.com/u/45469?u=6ab74b3b934f9659a90b588062c2c4328e40c6be&v=4&s=40", "name": "Jordan Harband", "commits": 4251},
"neauoire":{"rank": 16, "icon": "https://avatars.githubusercontent.com/u/1455726?u=493ac700a7358427f9bc76a0726412d85fb30e27&v=4&s=40", "name": "Devine Lu Linvega", "commits": 3962},
"rexim":{"rank": 17, "icon": "https://avatars.githubusercontent.com/u/165283?u=be7049b29d896ebf4fbb692c39736bb498b19e8d&v=4&s=40", "name": "Alexey Kutepov", "commits": 3861},
"dtolnay":{"rank": 18, "icon": "https://avatars.githubusercontent.com/u/1940490?u=42777c8876d7b6591798df666a82057394b8b0c8&v=4&s=40", "name": "David Tolnay", "commits": 3830},
"fabpot":{"rank": 19, "icon": "https://avatars.githubusercontent.com/u/47313?u=7ba05204271a726f8642ac15864e2f361b5c0198&v=4&s=40", "name": "Fabien Potencier", "commits": 3811},
"midudev":{"rank": 20, "icon": "https://avatars.githubusercontent.com/u/1561955?u=9ebfec769d2505d88ee746b7389353c23312bca1&v=4&s=40", "name": "Miguel Ángel Durán", "commits": 3690},
"nikic":{"rank": 21, "icon": "https://avatars.githubusercontent.com/u/216080?v=4&s=40", "name": "Nikita Popov", "commits": 3094},
"orta":{"rank": 22, "icon": "https://avatars.githubusercontent.com/u/49038?u=0b9ac5bf42a8ea2543a05191e150e0213456744e&v=4&s=40", "name": "Orta Therox", "commits": 3086},
"jiyinyiyong":{"rank": 23, "icon": "https://avatars.githubusercontent.com/u/449224?v=4&s=40", "name": "Jon", "commits": 3080},
"staltz":{"rank": 24, "icon": "https://avatars.githubusercontent.com/u/90512?u=05e5f183f1cc1ea55e28762eeee6a519a79ff3bc&v=4&s=40", "name": "André Staltz", "commits": 3074},
"manjunath5496":{"rank": 25, "icon": "https://avatars.githubusercontent.com/u/19967403?u=766b0cb1f5f9aaaf0ec39abf7d7b340c094f1fc3&v=4&s=40", "name": "Manjunath.R", "commits": 2988},
"joshlong":{"rank": 26, "icon": "https://avatars.githubusercontent.com/u/54473?v=4&s=40", "name": "Josh Long", "commits": 2964},
"jennybc":{"rank": 27, "icon": "https://avatars.githubusercontent.com/u/599454?u=8f8054b0f2bcb92f55859952cea69756ab29dd27&v=4&s=40", "name": "Jennifer Jenny Bryan", "commits": 2879},
"yegor256":{"rank": 28, "icon": "https://avatars.githubusercontent.com/u/526301?u=f5976db7f55b68ddd289b8dba2895527fb940c5a&v=4&s=40", "name": "Yegor Bugayenko", "commits": 2865},
"taylorotwell":{"rank": 29, "icon": "https://avatars.githubusercontent.com/u/463230?u=0c486fbe3a30dadd5c5981a9fbc3a0d269ca0c33&v=4&s=40", "name": "Taylor Otwell", "commits": 2782},
"photonstorm":{"rank": 30, "icon": "https://avatars.githubusercontent.com/u/164476?v=4&s=40", "name": "Richard Davey", "commits": 2621},
"jskeet":{"rank": 31, "icon": "https://avatars.githubusercontent.com/u/17011?v=4&s=40", "name": "Jon Skeet", "commits": 2585},
"torvalds":{"rank": 32, "icon": "https://avatars.githubusercontent.com/u/1024025?v=4&s=40", "name": "Linus Torvalds", "commits": 2519},
"marijnh":{"rank": 33, "icon": "https://avatars.githubusercontent.com/u/144427?u=a436bcccf762fe8955142810578b13db63e3173d&v=4&s=40", "name": "Marijn Haverbeke", "commits": 2476},
"vczh":{"rank": 34, "icon": "https://avatars.githubusercontent.com/u/773569?u=6e9b51d46dc1c12778b42b944d1ccaa3cda5446f&v=4&s=40", "name": "", "commits": 2348},
"juliasilge":{"rank": 35, "icon": "https://avatars.githubusercontent.com/u/12505835?u=44b4e9026210eae8096439b1637898226050fdb1&v=4&s=40", "name": "Julia Silge", "commits": 2348},
"samdark":{"rank": 36, "icon": "https://avatars.githubusercontent.com/u/47294?u=86b987bc1dab8dc2f633ac833d10e95b23a5688e&v=4&s=40", "name": "Alexander Makarov", "commits": 2252},
"mli":{"rank": 37, "icon": "https://avatars.githubusercontent.com/u/421857?u=4897d860de4cb4853db4662f065b51e0d46023ae&v=4&s=40", "name": "Mu Li", "commits": 2210},
"cclauss":{"rank": 38, "icon": "https://avatars.githubusercontent.com/u/3709715?u=0745d1d2473894c33f3b35f0b965d71cc9aec553&v=4&s=40", "name": "Christian Clauss", "commits": 2194},
"josevalim":{"rank": 39, "icon": "https://avatars.githubusercontent.com/u/9582?u=c00cf4c84840538f31a3a8a46fec9dcc7b0ff132&v=4&s=40", "name": "José Valim", "commits": 2191},
"Neo23x0":{"rank": 40, "icon": "https://avatars.githubusercontent.com/u/2851492?u=c08fdd9b75c1097410e101837974ce59a6a1fa09&v=4&s=40", "name": "Florian Roth", "commits": 2129},
"hanxiao":{"rank": 41, "icon": "https://avatars.githubusercontent.com/u/2041322?v=4&s=40", "name": "Han Xiao", "commits": 2096},
"weierophinney":{"rank": 42, "icon": "https://avatars.githubusercontent.com/u/25943?u=79dd2ea1d4d8855944715d09ee4c86215027fa80&v=4&s=40", "name": "Matthew Weier O'Phinney", "commits": 2015},
"CamDavidsonPilon":{"rank": 43, "icon": "https://avatars.githubusercontent.com/u/884032?u=d30e9ef30d20c25248f5d8acad88748d1c7a314a&v=4&s=40", "name": "Cameron Davidson-Pilon", "commits": 1985},
"hasherezade":{"rank": 44, "icon": "https://avatars.githubusercontent.com/u/3115348?u=ca64f917f82f2fc8b0afd3efec5b8cb54ab9d47c&v=4&s=40", "name": "", "commits": 1975},
"yihui":{"rank": 45, "icon": "https://avatars.githubusercontent.com/u/163582?v=4&s=40", "name": "Yihui Xie", "commits": 1946},
"sw-yx":{"rank": 46, "icon": "https://avatars.githubusercontent.com/u/6764957?u=97ad815028595b73b06ee4b0510e66bbe391228d&v=4&s=40", "name": "swyx", "commits": 1930},
"skydoves":{"rank": 47, "icon": "https://avatars.githubusercontent.com/u/24237865?u=3b20ba01607c3f8e7eef831394350af7ac9db475&v=4&s=40", "name": "Jaewoong Eum", "commits": 1805},
"andrewrk":{"rank": 48, "icon": "https://avatars.githubusercontent.com/u/106511?u=c5381a852bb5385fb4380496a39ab46106b2b6dd&v=4&s=40", "name": "Andrew Kelley", "commits": 1736},
"benawad":{"rank": 49, "icon": "https://avatars.githubusercontent.com/u/7872329?u=f41fcb80dc9ce32a809caf9a6c4d9bf31c6ae11a&v=4&s=40", "name": "Ben Awad", "commits": 1727},
"Shougo":{"rank": 50, "icon": "https://avatars.githubusercontent.com/u/41495?v=4&s=40", "name": "", "commits": 1706},
"nikomatsakis":{"rank": 51, "icon": "https://avatars.githubusercontent.com/u/155238?u=c09aaff33aa53ea99359e53bef06aa5058ac8d15&v=4&s=40", "name": "Niko Matsakis", "commits": 1703},
"dai-shi":{"rank": 52, "icon": "https://avatars.githubusercontent.com/u/490574?u=9109c61b2ea1f76f57bb7c288354230e8d0605a2&v=4&s=40", "name": "Daishi Kato", "commits": 1701},
"posva":{"rank": 53, "icon": "https://avatars.githubusercontent.com/u/664177?u=b213da9f4df34b2fc2063a2038dfd476e54ce4a5&v=4&s=40", "name": "Eduardo San Martin Morote", "commits": 1587},
"giswqs":{"rank": 54, "icon": "https://avatars.githubusercontent.com/u/5016453?u=5c0684de99c23b7461ac654b5cc73afc110172a9&v=4&s=40", "name": "Qiusheng Wu", "commits": 1575},
"nunomaduro":{"rank": 55, "icon": "https://avatars.githubusercontent.com/u/5457236?u=d5b7bffa91626108078a5a03c51ea3789579126d&v=4&s=40", "name": "Nuno Maduro", "commits": 1549},
"daneden":{"rank": 56, "icon": "https://avatars.githubusercontent.com/u/439365?u=91e4ef9348f3be4f60c965a730a7ea182f954826&v=4&s=40", "name": "Daniel Eden", "commits": 1538},
"egoist":{"rank": 57, "icon": "https://avatars.githubusercontent.com/u/8784712?u=80326db7c9ecac7f2783b10a98a307699a884cb2&v=4&s=40", "name": "EGOIST", "commits": 1520},
"geerlingguy":{"rank": 58, "icon": "https://avatars.githubusercontent.com/u/481677?u=81535aed4594f0b05f65becc0add71b7367a5f2c&v=4&s=40", "name": "Jeff Geerling", "commits": 1503},
"Aakashdeveloper":{"rank": 59, "icon": "https://avatars.githubusercontent.com/u/7868704?u=c096793ccffcb705e47356d697325ffb331f2c2a&v=4&s=40", "name": "Aakash ", "commits": 1494},
"Akryum":{"rank": 60, "icon": "https://avatars.githubusercontent.com/u/2798204?u=5e124c46566b10bfd4766f79308e772b11de2b0c&v=4&s=40", "name": "Guillaume Chau", "commits": 1492},
"youngyangyang04":{"rank": 61, "icon": "https://avatars.githubusercontent.com/u/8636020?u=bfb439d6152b4aaf21a79b6ddfff4df1c1e24818&v=4&s=40", "name": "程序员Carl", "commits": 1491},
"chjj":{"rank": 62, "icon": "https://avatars.githubusercontent.com/u/470564?v=4&s=40", "name": "Christopher Jeffrey JJ", "commits": 1474},
"EvanBacon":{"rank": 63, "icon": "https://avatars.githubusercontent.com/u/9664363?u=a4a9e93dc4305c91ced38b83d4c08186f7254b04&v=4&s=40", "name": "Evan Bacon", "commits": 1369},
"PySimpleGUI":{"rank": 64, "icon": "https://avatars.githubusercontent.com/u/46163555?u=6cb4187ba9736090c4f9d9d82d4972b826c20245&v=4&s=40", "name": "", "commits": 1353},
"sobolevn":{"rank": 65, "icon": "https://avatars.githubusercontent.com/u/4660275?u=42e203a9264267ffda774112d4edabc153981c9f&v=4&s=40", "name": "Nikita Sobolev", "commits": 1344},
"jezdez":{"rank": 66, "icon": "https://avatars.githubusercontent.com/u/1610?v=4&s=40", "name": "Jannis Leidel", "commits": 1331},
"be5invis":{"rank": 67, "icon": "https://avatars.githubusercontent.com/u/240091?u=c96c3142cd1ca26a5f86e962068054e12f3af7e7&v=4&s=40", "name": "Belleve", "commits": 1320},
"lukeed":{"rank": 68, "icon": "https://avatars.githubusercontent.com/u/5855893?v=4&s=40", "name": "Luke Edwards", "commits": 1319},
"Alvin9999":{"rank": 69, "icon": "https://avatars.githubusercontent.com/u/12132898?u=c89f584d1db765170a6e0dd3f69cd859b130059e&v=4&s=40", "name": "自由上网", "commits": 1298},
"Snailclimb":{"rank": 70, "icon": "https://avatars.githubusercontent.com/u/29880145?u=d2f8361655b9ebd973f5375acf014500bc0a4197&v=4&s=40", "name": "Guide哥", "commits": 1249},
"kazupon":{"rank": 71, "icon": "https://avatars.githubusercontent.com/u/72989?u=d333c3048e3d6f8ed2a476a3564dba1fa5288b86&v=4&s=40", "name": "kazuya kawaguchi", "commits": 1240},
"pissang":{"rank": 72, "icon": "https://avatars.githubusercontent.com/u/841551?u=d20f30b1e08a44195ef793cbdddc46abe72672d6&v=4&s=40", "name": "Yi Shen", "commits": 1233},
"ladyada":{"rank": 73, "icon": "https://avatars.githubusercontent.com/u/1214161?v=4&s=40", "name": "Limor \"Ladyada\" Fried", "commits": 1231},
"bbatsov":{"rank": 74, "icon": "https://avatars.githubusercontent.com/u/103882?v=4&s=40", "name": "Bozhidar Batsov", "commits": 1223},
"appleboy":{"rank": 75, "icon": "https://avatars.githubusercontent.com/u/21979?u=ad742a0b34a5461d12aa79cc441e5f6ca0453122&v=4&s=40", "name": "Bo-Yi Wu", "commits": 1214},
"coolsnowwolf":{"rank": 76, "icon": "https://avatars.githubusercontent.com/u/31687149?u=caa956c5f80318ea674625f9e9efa49c98335d74&v=4&s=40", "name": "", "commits": 1182},
"felangel":{"rank": 77, "icon": "https://avatars.githubusercontent.com/u/8855632?u=f798ce4cd8f8c6ea87e6b7b472c7c0b5471d93b5&v=4&s=40", "name": "Felix Angelov", "commits": 1169},
"mcollina":{"rank": 78, "icon": "https://avatars.githubusercontent.com/u/52195?u=08bcafa24337a298e1b874279fde515e2fb8f81d&v=4&s=40", "name": "Matteo Collina", "commits": 1163},
"liyasthomas":{"rank": 79, "icon": "https://avatars.githubusercontent.com/u/10395817?u=7f8107f5446550df97719d1a57677aea46a61926&v=4&s=40", "name": "Liyas Thomas", "commits": 1138},
"trekhleb":{"rank": 80, "icon": "https://avatars.githubusercontent.com/u/3000285?u=1e62782f227030b78b7aa78cbbcab5f8a24e658a&v=4&s=40", "name": "Oleksii Trekhleb", "commits": 1137},
"Seldaek":{"rank": 81, "icon": "https://avatars.githubusercontent.com/u/183678?u=5c0668a9af3d21ce3153666e4546d881216346bf&v=4&s=40", "name": "Jordi Boggiano", "commits": 1130},
"gorhill":{"rank": 82, "icon": "https://avatars.githubusercontent.com/u/585534?v=4&s=40", "name": "Raymond Hill", "commits": 1083},
"rafaelfranca":{"rank": 83, "icon": "https://avatars.githubusercontent.com/u/47848?u=41ccf0d1865a17f47d140f73a3293f1f3559fc0f&v=4&s=40", "name": "Rafael Mendonça França", "commits": 1072},
"willmcgugan":{"rank": 84, "icon": "https://avatars.githubusercontent.com/u/554369?u=8015a7d742d8bd7ee9d1efe30c138737d6098cd3&v=4&s=40", "name": "Will McGugan", "commits": 1064},
"zloirock":{"rank": 85, "icon": "https://avatars.githubusercontent.com/u/2213682?u=8b15e73a3320dde600389250b04b958996f8afe9&v=4&s=40", "name": "Denis Pushkarev", "commits": 1059},
"mrdoob":{"rank": 86, "icon": "https://avatars.githubusercontent.com/u/97088?u=95046da3776175b5f3d1ad2137704cd123e04d9e&v=4&s=40", "name": "", "commits": 1049},
"codingforentrepreneurs":{"rank": 87, "icon": "https://avatars.githubusercontent.com/u/8030945?u=b08d9f4c3a3d5106628cbc8b7f90e04e9bbacf9e&v=4&s=40", "name": "Coding For Entrepreneurs", "commits": 1042},
"xdvrx1":{"rank": 88, "icon": "https://avatars.githubusercontent.com/u/47092464?u=300c252d64e3feb6cfc5fcb441652bb7837c4784&v=4&s=40", "name": "", "commits": 1031},
"geohot":{"rank": 89, "icon": "https://avatars.githubusercontent.com/u/72895?u=64c16e3f87c708f1f3920331f1f6285f6529960e&v=4&s=40", "name": "George Hotz", "commits": 1024},
"chrisbanes":{"rank": 90, "icon": "https://avatars.githubusercontent.com/u/227486?u=4a13213e5ca361c28e16d6a2292ef03956a96cdf&v=4&s=40", "name": "Chris Banes", "commits": 1010},
"jessesquires":{"rank": 91, "icon": "https://avatars.githubusercontent.com/u/2301114?u=a2df0b32e2f3df0a87b85767bf2461a4a49df332&v=4&s=40", "name": "Jesse Squires", "commits": 998},
"benjamn":{"rank": 92, "icon": "https://avatars.githubusercontent.com/u/5750?u=95c71e43d35f4b2f7ea95474f5058bb51986f556&v=4&s=40", "name": "Ben Newman", "commits": 998},
"remy":{"rank": 93, "icon": "https://avatars.githubusercontent.com/u/13700?u=f98259de7691051ff225e4ff351888c8e7794276&v=4&s=40", "name": "Remy Sharp", "commits": 996},
"omariosouto":{"rank": 94, "icon": "https://avatars.githubusercontent.com/u/13791385?u=6f629f0aa7530d62552d7b746fc106531588f638&v=4&s=40", "name": "Mario Souto", "commits": 987},
"sorrycc":{"rank": 95, "icon": "https://avatars.githubusercontent.com/u/35128?u=0e80d87d2e3f3701a94d74a9cb6ff9f592cc7de5&v=4&s=40", "name": "chencheng 云谦", "commits": 969},
"mattn":{"rank": 96, "icon": "https://avatars.githubusercontent.com/u/10111?u=52c03ac58f0027d43f6708fcbc3c2913f195439c&v=4&s=40", "name": "", "commits": 967},
"GaelVaroquaux":{"rank": 97, "icon": "https://avatars.githubusercontent.com/u/208217?v=4&s=40", "name": "Gael Varoquaux", "commits": 962},
"answershuto":{"rank": 98, "icon": "https://avatars.githubusercontent.com/u/17812136?u=a971fad33a5fa6a69e9ad1cc8671fbab3b707c45&v=4&s=40", "name": "染陌同学", "commits": 943},
"dougwilson":{"rank": 99, "icon": "https://avatars.githubusercontent.com/u/67512?v=4&s=40", "name": "Douglas Wilson", "commits": 939},
"arvidn":{"rank": 100, "icon": "https://avatars.githubusercontent.com/u/661450?u=0776b7dc299640869e1b67765046d2f7057c78cf&v=4&s=40", "name": "Arvid Norberg", "commits": 931},
"marcan":{"rank": 101, "icon": "https://avatars.githubusercontent.com/u/98387?u=9e6fd6d25dfb88c1ea7dc10a662a40d3f4fa1df0&v=4&s=40", "name": "Hector Martin", "commits": 931},
"zkat":{"rank": 102, "icon": "https://avatars.githubusercontent.com/u/17535?u=5282eceb5e150ae40fbd2ea158197b8712cd29d7&v=4&s=40", "name": "Kat Marchán", "commits": 913},
"rstacruz":{"rank": 103, "icon": "https://avatars.githubusercontent.com/u/74385?u=3ff62084d6407dcd8ad75af2a73d9f0b60bfc368&v=4&s=40", "name": "Rico Sta. Cruz", "commits": 913},
"iamtrask":{"rank": 104, "icon": "https://avatars.githubusercontent.com/u/4328594?u=1596af74289701b6804123fd2f8ea9552dc03a1a&v=4&s=40", "name": "Andrew Trask", "commits": 905},
"Justineo":{"rank": 105, "icon": "https://avatars.githubusercontent.com/u/1726061?u=3490c34534d2a2a12e2e2221ffa2f476e1bbd77d&v=4&s=40", "name": "GU Yiling", "commits": 900},
"skyzh":{"rank": 106, "icon": "https://avatars.githubusercontent.com/u/4198311?u=fefe7b1c5ccabed1231c1a38930c1782ffecd550&v=4&s=40", "name": "Alex Chi", "commits": 900},
"huacnlee":{"rank": 107, "icon": "https://avatars.githubusercontent.com/u/5518?v=4&s=40", "name": "Jason Lee", "commits": 896},
"substack":{"rank": 108, "icon": "https://avatars.githubusercontent.com/u/12631?v=4&s=40", "name": "James Halliday", "commits": 891},
"fzaninotto":{"rank": 109, "icon": "https://avatars.githubusercontent.com/u/99944?u=24e77d6928aa3af0d7cb71cf5097fcdb9ed23c53&v=4&s=40", "name": "Francois Zaninotto", "commits": 882},
"josh":{"rank": 110, "icon": "https://avatars.githubusercontent.com/u/137?u=b2057aab3d62b3205fc5f01d315879fb2c71c711&v=4&s=40", "name": "Joshua Peek", "commits": 878},
"eddiejaoude":{"rank": 111, "icon": "https://avatars.githubusercontent.com/u/624760?v=4&s=40", "name": "Eddie Jaoude", "commits": 878},
"JakeWharton":{"rank": 112, "icon": "https://avatars.githubusercontent.com/u/66577?v=4&s=40", "name": "Jake Wharton", "commits": 871},
"odrotbohm":{"rank": 113, "icon": "https://avatars.githubusercontent.com/u/128577?v=4&s=40", "name": "Oliver Drotbohm", "commits": 869},
"sethvargo":{"rank": 114, "icon": "https://avatars.githubusercontent.com/u/408570?u=8a3f94bc4baf45b52a80181ebc9e0b66572fad5d&v=4&s=40", "name": "Seth Vargo", "commits": 849},
"wangfupeng1988":{"rank": 115, "icon": "https://avatars.githubusercontent.com/u/9583120?u=69f3d8f6b12b22c218c1428c0925472d956c8cd2&v=4&s=40", "name": "王福朋", "commits": 849},
"zenorocha":{"rank": 116, "icon": "https://avatars.githubusercontent.com/u/398893?u=29ba95a288275eefa4a6b1454156924f6dd3a15f&v=4&s=40", "name": "Zeno Rocha", "commits": 840},
"odersky":{"rank": 117, "icon": "https://avatars.githubusercontent.com/u/795990?u=826577816eda6d92106ef011bf62cfba6cdd5add&v=4&s=40", "name": "", "commits": 834},
"tonsky":{"rank": 118, "icon": "https://avatars.githubusercontent.com/u/285292?u=f2b9cbda2dba12d9ae63c61b9ff8567c0f0ee957&v=4&s=40", "name": "Nikita Prokopov", "commits": 831},
"fatih":{"rank": 119, "icon": "https://avatars.githubusercontent.com/u/438920?u=a0bcca9e7720619bd9fc7979c1d2971f752164f5&v=4&s=40", "name": "Fatih Arslan", "commits": 830},
"domenic":{"rank": 120, "icon": "https://avatars.githubusercontent.com/u/617481?v=4&s=40", "name": "Domenic Denicola", "commits": 822},
"onevcat":{"rank": 121, "icon": "https://avatars.githubusercontent.com/u/1019875?u=34477b070af505986e26066dfa6a5d2d64f319b6&v=4&s=40", "name": "Wei Wang", "commits": 820},
"buckyroberts":{"rank": 122, "icon": "https://avatars.githubusercontent.com/u/8547538?u=8a4be84ff4870a332fe94c11fca02b432fb9f83e&v=4&s=40", "name": "Bucky Roberts", "commits": 807},
"PascalPrecht":{"rank": 123, "icon": "https://avatars.githubusercontent.com/u/445106?u=b9e460c01113415b3338f873199d7dbd4d29d9cd&v=4&s=40", "name": "r4bbit.eth", "commits": 804},
"unknwon":{"rank": 124, "icon": "https://avatars.githubusercontent.com/u/2946214?u=f7db4e71ec55cfd9d462c7cdb041e5dfb8174efc&v=4&s=40", "name": "Joe Chen", "commits": 802},
"ekmett":{"rank": 125, "icon": "https://avatars.githubusercontent.com/u/304657?v=4&s=40", "name": "Edward Kmett", "commits": 793},
"markerikson":{"rank": 126, "icon": "https://avatars.githubusercontent.com/u/1128784?u=dce7b188b2fd38805f7528c60e332a6bfbd92f19&v=4&s=40", "name": "Mark Erikson", "commits": 788},
"Rich-Harris":{"rank": 127, "icon": "https://avatars.githubusercontent.com/u/1162160?v=4&s=40", "name": "Rich Harris", "commits": 786},
"devongovett":{"rank": 128, "icon": "https://avatars.githubusercontent.com/u/19409?u=92d068dffb5d6885767709af7bc4ef8ddcb356b2&v=4&s=40", "name": "Devon Govett", "commits": 782},
"kamranahmedse":{"rank": 129, "icon": "https://avatars.githubusercontent.com/u/4921183?u=9a67bfd198f1a73f262d08b53eeb6ad2befc572f&v=4&s=40", "name": "Kamran Ahmed", "commits": 777},
"normanmaurer":{"rank": 130, "icon": "https://avatars.githubusercontent.com/u/439362?u=f1963e1e7ca28c94c291cf1a2c04c8adc63e54d2&v=4&s=40", "name": "Norman Maurer", "commits": 773},
"ThePrimeagen":{"rank": 131, "icon": "https://avatars.githubusercontent.com/u/4458174?u=f59d4f5b38134faff67b8a231591f1288ba51a8e&v=4&s=40", "name": "", "commits": 743},
"miguelgrinberg":{"rank": 132, "icon": "https://avatars.githubusercontent.com/u/2715854?v=4&s=40", "name": "Miguel Grinberg", "commits": 729},
"SpikeKing":{"rank": 133, "icon": "https://avatars.githubusercontent.com/u/10265720?u=38dac7e9193dc2876ac753f871ee939f1088e5fb&v=4&s=40", "name": "C. L. Wang", "commits": 722},
"overtrue":{"rank": 134, "icon": "https://avatars.githubusercontent.com/u/1472352?u=72f261973db954faf4a64987ee3f7e7baf423ded&v=4&s=40", "name": "安正超", "commits": 721},
"schneems":{"rank": 135, "icon": "https://avatars.githubusercontent.com/u/59744?u=dcc56246ab9ed7f43103e10a1b09b6cecf8599cf&v=4&s=40", "name": "Richard Schneeman", "commits": 719},
"kujian":{"rank": 136, "icon": "https://avatars.githubusercontent.com/u/3055447?u=0152db3b7f55cc23aeb328f8595851c9f6277cb6&v=4&s=40", "name": "前端开发博客", "commits": 719},
"ogrisel":{"rank": 137, "icon": "https://avatars.githubusercontent.com/u/89061?v=4&s=40", "name": "Olivier Grisel", "commits": 717},
"feross":{"rank": 138, "icon": "https://avatars.githubusercontent.com/u/121766?v=4&s=40", "name": "Feross Aboukhadijeh", "commits": 714},
"alanhamlett":{"rank": 139, "icon": "https://avatars.githubusercontent.com/u/522344?u=81199fa9902b27d90529eb171139d6bba53a415a&v=4&s=40", "name": "Alan Hamlett", "commits": 711},
"afc163":{"rank": 140, "icon": "https://avatars.githubusercontent.com/u/507615?u=63a8ef8e8876c4c1fad07a7737684f5281fedaaa&v=4&s=40", "name": "", "commits": 708},
"willianjusten":{"rank": 141, "icon": "https://avatars.githubusercontent.com/u/3991845?u=45a2712ccbcc6740b8845aa0a3f40f6d226552cf&v=4&s=40", "name": "Willian Justen ", "commits": 704},
"dntzhang":{"rank": 142, "icon": "https://avatars.githubusercontent.com/u/7917954?u=1de3681a623a9480ad5dfbc5c8fadd477d1b060d&v=4&s=40", "name": "当耐特", "commits": 701},
"fuzhengwei":{"rank": 143, "icon": "https://avatars.githubusercontent.com/u/3761578?u=5f969f4e0eedb1210a1eae515a6e2df31c16f472&v=4&s=40", "name": "小傅哥", "commits": 691},
"3b1b":{"rank": 144, "icon": "https://avatars.githubusercontent.com/u/11601040?u=ccd223915efaad0958c195ce57bf46ab40d67873&v=4&s=40", "name": "Grant Sanderson", "commits": 691},
"ProgrammingHero1":{"rank": 145, "icon": "https://avatars.githubusercontent.com/u/53802153?u=afafdc1e616661db825c36dfe796c6f3c823eb15&v=4&s=40", "name": "Programming Hero", "commits": 683},
"liuyubobobo":{"rank": 146, "icon": "https://avatars.githubusercontent.com/u/2057443?u=cfa90bc9ee80db69930dbbd6a16fe5eae4b607d6&v=4&s=40", "name": "Yubo Liu", "commits": 682},
"LukeSmithxyz":{"rank": 147, "icon": "https://avatars.githubusercontent.com/u/29150857?v=4&s=40", "name": "Luke Smith", "commits": 682},
"shiffman":{"rank": 148, "icon": "https://avatars.githubusercontent.com/u/191758?u=a6f4a24c363ab8271c20754e1bdcef6ce4020360&v=4&s=40", "name": "Daniel Shiffman", "commits": 680},
"mame":{"rank": 149, "icon": "https://avatars.githubusercontent.com/u/21557?v=4&s=40", "name": "Yusuke Endoh", "commits": 672},
"LeaVerou":{"rank": 150, "icon": "https://avatars.githubusercontent.com/u/175836?u=af5ecaec009f4cf22e5978db7ba974c19585d459&v=4&s=40", "name": "Lea Verou", "commits": 667},
"calebporzio":{"rank": 151, "icon": "https://avatars.githubusercontent.com/u/3670578?u=b03293e8de4d6815ff792114f948609c0fa72d0d&v=4&s=40", "name": "Caleb Porzio", "commits": 664},
"tidwall":{"rank": 152, "icon": "https://avatars.githubusercontent.com/u/1156077?u=a69712c52c568b3c3bfc7073f9a4bdc5a33b8239&v=4&s=40", "name": "Josh Baker", "commits": 664},
"felixge":{"rank": 153, "icon": "https://avatars.githubusercontent.com/u/15000?u=f9b953343c6ce2e8c88ce31e8fcc45940d098890&v=4&s=40", "name": "Felix Geisendörfer", "commits": 644},
"rsms":{"rank": 154, "icon": "https://avatars.githubusercontent.com/u/47046?u=131e2a6b56d34625caaad1128b7cb8d70f213231&v=4&s=40", "name": "Rasmus", "commits": 643},
"bailicangdu":{"rank": 155, "icon": "https://avatars.githubusercontent.com/u/20297227?u=e242a737826e2e0d44245a9bb1129a0948334004&v=4&s=40", "name": "cangdu", "commits": 640},
"alex":{"rank": 156, "icon": "https://avatars.githubusercontent.com/u/772?u=7c00c7c8ac3691da556d7686e16ff08b797d4a38&v=4&s=40", "name": "Alex Gaynor", "commits": 638},
"nihui":{"rank": 157, "icon": "https://avatars.githubusercontent.com/u/171016?u=44cd03b22b0e7462dc094e8e520b52acb87e0fdf&v=4&s=40", "name": "", "commits": 635},
"antonbabenko":{"rank": 158, "icon": "https://avatars.githubusercontent.com/u/393243?u=942cb9dc4cee4340f2b1ededd903a293101999de&v=4&s=40", "name": "Anton Babenko", "commits": 633},
"KieSun":{"rank": 159, "icon": "https://avatars.githubusercontent.com/u/11811888?u=2d330564df93a5291ea8f261c588670ae01f20de&v=4&s=40", "name": "yck", "commits": 624},
"nelsonic":{"rank": 160, "icon": "https://avatars.githubusercontent.com/u/194400?u=405fb897c18f414ea8c4f4f2613fbef605855f02&v=4&s=40", "name": "Nelson", "commits": 622},
"nvie":{"rank": 161, "icon": "https://avatars.githubusercontent.com/u/83844?u=9dc6d501512fa27781761de35ae8a057a0348ec4&v=4&s=40", "name": "Vincent Driessen", "commits": 620},
"kunal-kushwaha":{"rank": 162, "icon": "https://avatars.githubusercontent.com/u/42698533?u=0b64f10aa6528ef363a9fe0eb802da40db71cd14&v=4&s=40", "name": "Kunal Kushwaha", "commits": 618},
"davidtmiller":{"rank": 163, "icon": "https://avatars.githubusercontent.com/u/8400627?u=1d25916fae20f2d7c6860b51125fb01f92a08377&v=4&s=40", "name": "David Miller", "commits": 618},
"KyleAMathews":{"rank": 164, "icon": "https://avatars.githubusercontent.com/u/71047?u=1e37a3794af3d8cdc082692d88c64805dd47e610&v=4&s=40", "name": "Kyle Mathews", "commits": 612},
"wasabeef":{"rank": 165, "icon": "https://avatars.githubusercontent.com/u/1833474?v=4&s=40", "name": "Daichi Furiya", "commits": 603},
"nolanlawson":{"rank": 166, "icon": "https://avatars.githubusercontent.com/u/283842?v=4&s=40", "name": "Nolan Lawson", "commits": 600},
"kripken":{"rank": 167, "icon": "https://avatars.githubusercontent.com/u/173661?u=4f553536b1cece11ff423e9baea8a81cde80777d&v=4&s=40", "name": "Alon Zakai", "commits": 594},
"wu-sheng":{"rank": 168, "icon": "https://avatars.githubusercontent.com/u/5441976?u=81295cafac69af5a655b94b73e839f10e6e1657b&v=4&s=40", "name": "吴晟 Wu Sheng", "commits": 587},
"jonhoo":{"rank": 169, "icon": "https://avatars.githubusercontent.com/u/176295?v=4&s=40", "name": "Jon Gjengset", "commits": 583},
"YunaiV":{"rank": 170, "icon": "https://avatars.githubusercontent.com/u/2015545?u=cb494dbc67c9004f32a4535f466e75b9f8702627&v=4&s=40", "name": "芋道源码", "commits": 579},
"wcandillon":{"rank": 171, "icon": "https://avatars.githubusercontent.com/u/306134?v=4&s=40", "name": "William Candillon", "commits": 576},
"jlengstorf":{"rank": 172, "icon": "https://avatars.githubusercontent.com/u/163561?u=960f83de8eb09da33548895a8a9e269aad1d3cf7&v=4&s=40", "name": "Jason Lengstorf", "commits": 576},
"rsc":{"rank": 173, "icon": "https://avatars.githubusercontent.com/u/104030?u=7776f9d68ea1bc349af0227c03fca30350a05477&v=4&s=40", "name": "Russ Cox", "commits": 570},
"doggy8088":{"rank": 174, "icon": "https://avatars.githubusercontent.com/u/88981?u=dbe051f354e8b03759d10e78a4cc62b60cc61fe6&v=4&s=40", "name": "Will 保哥", "commits": 568},
"developit":{"rank": 175, "icon": "https://avatars.githubusercontent.com/u/105127?u=9dbda1907e83e069f6f1ee68b77111f784fae663&v=4&s=40", "name": "Jason Miller", "commits": 566},
"donnemartin":{"rank": 176, "icon": "https://avatars.githubusercontent.com/u/5458997?u=f1007b583e55e7ccfb6ccf0e200051156112dd9b&v=4&s=40", "name": "Donne Martin", "commits": 566},
"rrousselGit":{"rank": 177, "icon": "https://avatars.githubusercontent.com/u/20165741?u=192e2eb9d75e4c2f4af4a114a11230bbe0aa76b5&v=4&s=40", "name": "Remi Rousselet", "commits": 563},
"felipefialho":{"rank": 178, "icon": "https://avatars.githubusercontent.com/u/3603793?u=c6b825c85da562a7c915289087dab96783a808a4&v=4&s=40", "name": "Felipe Fialho", "commits": 555},
"jaredpalmer":{"rank": 179, "icon": "https://avatars.githubusercontent.com/u/4060187?u=a9b891a1425d4aec44e26898e75410c7b41e5466&v=4&s=40", "name": "Jared Palmer", "commits": 543},
"chenglou":{"rank": 180, "icon": "https://avatars.githubusercontent.com/u/1909539?v=4&s=40", "name": "Cheng Lou", "commits": 535},
"mjackson":{"rank": 181, "icon": "https://avatars.githubusercontent.com/u/92839?u=2727b5ab382f6b2f3be84a257c2dcdc50243d78f&v=4&s=40", "name": "Michael Jackson", "commits": 534},
"velopert":{"rank": 182, "icon": "https://avatars.githubusercontent.com/u/17202261?u=c448958b8ee253314a64b1d753833de3bbf8a4ca&v=4&s=40", "name": "Minjun Kim", "commits": 517},
"timneutkens":{"rank": 183, "icon": "https://avatars.githubusercontent.com/u/6324199?u=4bf20067bc68295cbc46fd57c3fe88d508f3305a&v=4&s=40", "name": "Tim Neutkens", "commits": 517},
"amatsuda":{"rank": 184, "icon": "https://avatars.githubusercontent.com/u/11493?v=4&s=40", "name": "Akira Matsuda", "commits": 513},
"munificent":{"rank": 185, "icon": "https://avatars.githubusercontent.com/u/46275?v=4&s=40", "name": "Bob Nystrom", "commits": 511},
"azer":{"rank": 186, "icon": "https://avatars.githubusercontent.com/u/13072?u=abce9a3d5cd264597a674c65cc0051a8bb4ddfa3&v=4&s=40", "name": "", "commits": 510},
"amusi":{"rank": 187, "icon": "https://avatars.githubusercontent.com/u/22436957?u=96a326f8d9c37e32abbc78f5dc872d3898a65f23&v=4&s=40", "name": "Amusi", "commits": 504},
"griesemer":{"rank": 188, "icon": "https://avatars.githubusercontent.com/u/8528975?u=f805aea1bf2bea2dbd5c2aaed2cefcdab2205ef2&v=4&s=40", "name": "Robert Griesemer", "commits": 501},
"csharpfritz":{"rank": 189, "icon": "https://avatars.githubusercontent.com/u/78577?u=44d2e2ca047b6f7ac60fcd3a244044e69df03e0f&v=4&s=40", "name": "Jeffrey T. Fritz", "commits": 500},
"tiangolo":{"rank": 190, "icon": "https://avatars.githubusercontent.com/u/1326112?u=5cad72c846b7aba2e960546af490edc7375dafc4&v=4&s=40", "name": "Sebastián Ramírez", "commits": 496},
"dusty-nv":{"rank": 191, "icon": "https://avatars.githubusercontent.com/u/15352619?u=2931352d1f495aba1c172e0c6ae5bfeac8152b06&v=4&s=40", "name": "Dustin Franklin", "commits": 493},
"wesbos":{"rank": 192, "icon": "https://avatars.githubusercontent.com/u/176013?u=1d436e62dc32dbbf1bfefb4d658cd67553154c42&v=4&s=40", "name": "Wes Bos", "commits": 489},
"purcell":{"rank": 193, "icon": "https://avatars.githubusercontent.com/u/5636?u=06a9d72c54f47886ab65935cdf2e33da9562e569&v=4&s=40", "name": "Steve Purcell", "commits": 485},
"dkhamsing":{"rank": 194, "icon": "https://avatars.githubusercontent.com/u/4723115?u=00a1cc211c18c5386612882221611dda9a497048&v=4&s=40", "name": "", "commits": 482},
"john-smilga":{"rank": 195, "icon": "https://avatars.githubusercontent.com/u/42133389?u=9d63b6d71fba139347cddf2c840a858c8ff97168&v=4&s=40", "name": "John Smilga", "commits": 478},
"matyhtf":{"rank": 196, "icon": "https://avatars.githubusercontent.com/u/2017766?u=7ff6fb8a532fa2992dc0cb8aa41571ebf2d37138&v=4&s=40", "name": "韩天峰-Rango", "commits": 478},
"LauraBeatris":{"rank": 197, "icon": "https://avatars.githubusercontent.com/u/48022589?u=dbef0847e650ebb0ffa9602a67c9cb4735aaadfc&v=4&s=40", "name": "Laura Beatris", "commits": 477},
"topjohnwu":{"rank": 198, "icon": "https://avatars.githubusercontent.com/u/7337301?v=4&s=40", "name": "John Wu", "commits": 475},
"shuding":{"rank": 199, "icon": "https://avatars.githubusercontent.com/u/3676859?u=a866d19c4fce64bf67a084eb32f29bb6e84020a5&v=4&s=40", "name": "Shu Ding", "commits": 474},
"ept":{"rank": 200, "icon": "https://avatars.githubusercontent.com/u/27544?u=b33b13b1e9fc319880ca8a78f758299c2ebb6df1&v=4&s=40", "name": "Martin Kleppmann", "commits": 469},
"yole":{"rank": 201, "icon": "https://avatars.githubusercontent.com/u/46553?u=9432e5ac962ed0491b2f86a9540700225b49ce31&v=4&s=40", "name": "Dmitry Jemerov", "commits": 466},
"phuslu":{"rank": 202, "icon": "https://avatars.githubusercontent.com/u/195836?u=701cb4099e8abed179a130f1aebee7cd8d68ebde&v=4&s=40", "name": "", "commits": 464},
"yuanyan":{"rank": 203, "icon": "https://avatars.githubusercontent.com/u/677114?u=997e879c8ab136935baaaa7153e800a7634b9da9&v=4&s=40", "name": "元彦", "commits": 463},
"tomchristie":{"rank": 204, "icon": "https://avatars.githubusercontent.com/u/647359?u=afcdb67ec485900d025d18270a115085e3f0f909&v=4&s=40", "name": "Tom Christie", "commits": 458},
"ahmetb":{"rank": 205, "icon": "https://avatars.githubusercontent.com/u/159209?u=a32d91ab1d990c840ded108a7f1ef06497ba9bb5&v=4&s=40", "name": "Ahmet Alp Balkan", "commits": 455},
"MylesBorins":{"rank": 206, "icon": "https://avatars.githubusercontent.com/u/498775?v=4&s=40", "name": "Myles Borins", "commits": 452},
"diego3g":{"rank": 207, "icon": "https://avatars.githubusercontent.com/u/2254731?u=3d3d7f89539bc7602f2f35d83288e33b44dd70a7&v=4&s=40", "name": "Diego Fernandes", "commits": 451},
"swankjesse":{"rank": 208, "icon": "https://avatars.githubusercontent.com/u/133019?u=e74de21cd4a2948b635fcc48cf7b2f4957263915&v=4&s=40", "name": "Jesse Wilson", "commits": 442},
"dsyer":{"rank": 209, "icon": "https://avatars.githubusercontent.com/u/124075?u=0126f73c071aade850b6016df3d4ce273914a094&v=4&s=40", "name": "Dave Syer", "commits": 442},
"Germey":{"rank": 210, "icon": "https://avatars.githubusercontent.com/u/8678661?u=52bb00d46febb9184a438682f9706135b84bbda6&v=4&s=40", "name": "崔庆才丨静觅", "commits": 442},
"rwieruch":{"rank": 211, "icon": "https://avatars.githubusercontent.com/u/2479967?u=cba76c8678af8e63ee2dd32853a4e262b35f9ac0&v=4&s=40", "name": "Robin Wieruch", "commits": 440},
"pyricau":{"rank": 212, "icon": "https://avatars.githubusercontent.com/u/557033?u=e4b85cd6117b8912cd783f7152c32298794725f5&v=4&s=40", "name": "py - Pierre Yves Ricau", "commits": 435},
"robdodson":{"rank": 213, "icon": "https://avatars.githubusercontent.com/u/1066253?v=4&s=40", "name": "Rob Dodson", "commits": 433},
"TooTallNate":{"rank": 214, "icon": "https://avatars.githubusercontent.com/u/71256?u=d6a9598cd7963ae290923ab12afeff947f542f80&v=4&s=40", "name": "Nathan Rajlich", "commits": 430},
"johnpapa":{"rank": 215, "icon": "https://avatars.githubusercontent.com/u/1202528?u=776ce7b4fb82b0c7e69b38f532c73abf4889dd1d&v=4&s=40", "name": "John Papa", "commits": 429},
"walkor":{"rank": 216, "icon": "https://avatars.githubusercontent.com/u/6073368?u=bbc6e9db79d25be8a467c86f54dbdce3ca0fcd1a&v=4&s=40", "name": "", "commits": 427},
"BretFisher":{"rank": 217, "icon": "https://avatars.githubusercontent.com/u/792287?u=2fc247bd9edc4019386a7c42123b4274e4e21849&v=4&s=40", "name": "Bret Fisher", "commits": 422},
"BruceEckel":{"rank": 218, "icon": "https://avatars.githubusercontent.com/u/1001900?v=4&s=40", "name": "Bruce Eckel", "commits": 421},
"ashishpatel26":{"rank": 219, "icon": "https://avatars.githubusercontent.com/u/3095771?u=522d8855c070c0af151b27becc02052e34849d4e&v=4&s=40", "name": "Ashish Patel", "commits": 421},
"nayuki":{"rank": 220, "icon": "https://avatars.githubusercontent.com/u/672172?v=4&s=40", "name": "Nayuki", "commits": 419},
"fdaciuk":{"rank": 221, "icon": "https://avatars.githubusercontent.com/u/487669?u=44dce0d2f0149d3e0bc765eef93fe916cdb3a7c6&v=4&s=40", "name": "Fernando Daciuk", "commits": 417},
"dataprofessor":{"rank": 222, "icon": "https://avatars.githubusercontent.com/u/51851491?u=dd40802af100a9f627a92ed707e997c2528c7b07&v=4&s=40", "name": "Chanin Nantasenamat", "commits": 416},
"sharkdp":{"rank": 223, "icon": "https://avatars.githubusercontent.com/u/4209276?u=e6c4022c315b6cbecd5968ec256f4b02885eba41&v=4&s=40", "name": "David Peter", "commits": 413},
"jpetazzo":{"rank": 224, "icon": "https://avatars.githubusercontent.com/u/171481?v=4&s=40", "name": "Jérôme Petazzoni", "commits": 405},
"jakearchibald":{"rank": 225, "icon": "https://avatars.githubusercontent.com/u/93594?v=4&s=40", "name": "Jake Archibald", "commits": 405},
"davidfowl":{"rank": 226, "icon": "https://avatars.githubusercontent.com/u/95136?u=7c54b5f134fd50fa67af8d3e7604f51626242985&v=4&s=40", "name": "David Fowler", "commits": 398},
"aantonop":{"rank": 227, "icon": "https://avatars.githubusercontent.com/u/1181915?u=9be6623b23422115517dfef1f75a8375efe7f0b9&v=4&s=40", "name": "Andreas M. Antonopoulos", "commits": 396},
"alsotang":{"rank": 228, "icon": "https://avatars.githubusercontent.com/u/1147375?u=90d8bdbad51946eafd35ec74be14606fe034fbdc&v=4&s=40", "name": "", "commits": 393},
"graydon":{"rank": 229, "icon": "https://avatars.githubusercontent.com/u/14097?v=4&s=40", "name": "Graydon Hoare", "commits": 391},
"ariya":{"rank": 230, "icon": "https://avatars.githubusercontent.com/u/7288?u=d84135ccc1b777c4813c7f377ea8219279ba24ff&v=4&s=40", "name": "Ariya Hidayat", "commits": 390},
"zendy199x":{"rank": 231, "icon": "https://avatars.githubusercontent.com/u/50132805?u=b2ca1413861a60cfc2800eaca18759b874d66ed3&v=4&s=40", "name": "Zendy", "commits": 389},
"jart":{"rank": 232, "icon": "https://avatars.githubusercontent.com/u/49262?u=ac68933ab61c639ab59ae693a41ae89cd874c16e&v=4&s=40", "name": "Justine Tunney", "commits": 385},
"vxunderground":{"rank": 233, "icon": "https://avatars.githubusercontent.com/u/57078196?u=f19884841c402deb8c9d4c11318b1dc9e4b65c25&v=4&s=40", "name": "", "commits": 385},
"JamesNK":{"rank": 234, "icon": "https://avatars.githubusercontent.com/u/303201?u=a4521438844aae7f844f8717a79a9858d6c805da&v=4&s=40", "name": "James Newton-King", "commits": 382},
"codebytere":{"rank": 235, "icon": "https://avatars.githubusercontent.com/u/2036040?u=20f9411c9d609218913b74cf2ad0dc326ccab0b2&v=4&s=40", "name": "Shelley Vohr", "commits": 381},
"egonSchiele":{"rank": 236, "icon": "https://avatars.githubusercontent.com/u/97219?v=4&s=40", "name": "Aditya Bhargava", "commits": 378},
"acgotaku":{"rank": 237, "icon": "https://avatars.githubusercontent.com/u/1191834?u=b9f1bf747e4f71981b355949541cd97b65a95a48&v=4&s=40", "name": "雪月秋水", "commits": 377},
"andrebaltieri":{"rank": 238, "icon": "https://avatars.githubusercontent.com/u/965305?u=87f6a986e5170c7bce11ba138df12410ad9a1814&v=4&s=40", "name": "Andre Baltieri", "commits": 374},
"rmosolgo":{"rank": 239, "icon": "https://avatars.githubusercontent.com/u/2231765?u=f440b90427dd354e5e689683e36b5bf812c8791a&v=4&s=40", "name": "Robert Mosolgo", "commits": 370},
"bojone":{"rank": 240, "icon": "https://avatars.githubusercontent.com/u/9159613?u=e823e79e3f9227b5b6d90fcde9a443d16cc4ce8d&v=4&s=40", "name": "苏剑林Jianlin Su", "commits": 370},
"pydanny":{"rank": 241, "icon": "https://avatars.githubusercontent.com/u/62857?u=66f981da66da5560af7d2f8b9f7b895ec83a65e0&v=4&s=40", "name": "Daniel Roy Greenfeld", "commits": 362},
"aphyr":{"rank": 242, "icon": "https://avatars.githubusercontent.com/u/3748?u=dccc81fed92688be372ddb452515f17d7cd81a6c&v=4&s=40", "name": "Kyle Kingsbury", "commits": 358},
"AtsushiSakai":{"rank": 243, "icon": "https://avatars.githubusercontent.com/u/3813847?v=4&s=40", "name": "Atsushi Sakai", "commits": 355},
"rodrigobranas":{"rank": 244, "icon": "https://avatars.githubusercontent.com/u/7491283?u=af373a343dd451402953c7f2e82fc92c78550652&v=4&s=40", "name": "Rodrigo Branas", "commits": 354},
"ademilter":{"rank": 245, "icon": "https://avatars.githubusercontent.com/u/187922?u=49f5bb9bca107a617cd9f838b63432249b22d702&v=4&s=40", "name": "Adem ilter", "commits": 354},
"acdlite":{"rank": 246, "icon": "https://avatars.githubusercontent.com/u/3624098?u=b661e4a918cbba0cd2124afbd0b18685137a574e&v=4&s=40", "name": "Andrew Clark", "commits": 352},
"scopsy":{"rank": 247, "icon": "https://avatars.githubusercontent.com/u/8872447?u=c813c70e3b9ddcf2f13767d236b10110dfccd834&v=4&s=40", "name": "Dima Grossman", "commits": 352},
"GeekTrainer":{"rank": 248, "icon": "https://avatars.githubusercontent.com/u/6109729?u=33496c8e09bce2e455de0e0aa4b8bdf697b77c7c&v=4&s=40", "name": "Christopher Harrison", "commits": 341},
"robbiehanson":{"rank": 249, "icon": "https://avatars.githubusercontent.com/u/304604?u=c5e0f098f71e8a1896ad5c7e0a9fc701d853eb22&v=4&s=40", "name": "Robbie Hanson", "commits": 340},
"cloudwu":{"rank": 250, "icon": "https://avatars.githubusercontent.com/u/729648?v=4&s=40", "name": "云风", "commits": 339},
"jspahrsummers":{"rank": 251, "icon": "https://avatars.githubusercontent.com/u/432536?u=2f2cc11d83c0ec8abae7d94ceb6103b871886a5b&v=4&s=40", "name": "Justin Spahr-Summers", "commits": 339},
"hasinhayder":{"rank": 252, "icon": "https://avatars.githubusercontent.com/u/490779?u=cdadbb92b2ef6713aaa8caf69c455b676eb8cb77&v=4&s=40", "name": "Hasin Hayder", "commits": 335},
"FaztTech":{"rank": 253, "icon": "https://avatars.githubusercontent.com/u/13667358?u=7e71f086794b9271965a4f234bf90c5fcbb70fc1&v=4&s=40", "name": "Fazt", "commits": 333},
"3gstudent":{"rank": 254, "icon": "https://avatars.githubusercontent.com/u/15814408?u=7355dbeed0bf313673a3fd339f8ab5ef2e0377bf&v=4&s=40", "name": "", "commits": 332},
"cassidoo":{"rank": 255, "icon": "https://avatars.githubusercontent.com/u/1454517?u=92a133438fecfefc65c4c73143a0f717bd5e7515&v=4&s=40", "name": "Cassidy Williams", "commits": 331},
"CharlesCreativeContent":{"rank": 256, "icon": "https://avatars.githubusercontent.com/u/62077627?u=9e02f0380fe0e1cf82f4343f5621c82645ad67e5&v=4&s=40", "name": "Shawn Charles", "commits": 330}}
